[
  {
    "symbolicName": "1.6.4",
    "version": {
      "major": -1,
      "minor": -1,
      "micro": -1,
      "qualifier": ""
    },
    "jarFileFingerprint": "3a302dff5b7caec11ff38c970aab99ad0c0a404e",
    "jarFileModificationDate": "2014-01-18T12:01:19+11:00",
    "location": "/Users/timothyboye/ICT Freelance/Minecraft/Mod 0/jars/versions/1.6.4/1.6.4.jar",
    "javaRuntime": false
  },
  {
    "symbolicName": "lwjgl_util-2.9.0",
    "version": {
      "major": -1,
      "minor": -1,
      "micro": -1,
      "qualifier": ""
    },
    "jarFileFingerprint": "a778846b64008fc7f48ead2377f034e547991699",
    "jarFileModificationDate": "2014-01-18T11:45:13+11:00",
    "location": "/Users/timothyboye/ICT Freelance/Minecraft/Mod 0/jars/libraries/org/lwjgl/lwjgl/lwjgl_util/2.9.0/lwjgl_util-2.9.0.jar",
    "javaRuntime": false
  },
  {
    "symbolicName": "jre",
    "version": {
      "major": 1,
      "minor": 0,
      "micro": 0,
      "qualifier": ""
    },
    "jarFileFingerprint": "92ebbef37d1a48a2e460d258e1b7a141a0ca6a28",
    "jarFileModificationDate": "2013-10-11T05:22:21+11:00",
    "location": "/System/Library/Java/JavaVirtualMachines/1.6.0.jdk/Contents/Home/lib/ext/sunjce_provider.jar",
    "javaRuntime": true
  },
  {
    "symbolicName": "jre",
    "version": {
      "major": 1,
      "minor": 0,
      "micro": 0,
      "qualifier": ""
    },
    "jarFileFingerprint": "6aac3a170091ffb8ce43705c47915a7072a6fbc5",
    "jarFileModificationDate": "2013-10-11T05:28:14+11:00",
    "location": "/System/Library/Java/JavaVirtualMachines/1.6.0.jdk/Contents/Home/lib/ext/sunpkcs11.jar",
    "javaRuntime": true
  },
  {
    "symbolicName": "bcprov",
    "version": {
      "major": 1,
      "minor": 47,
      "micro": 0,
      "qualifier": ""
    },
    "jarFileFingerprint": "b6f5d9926b0afbde9f4dbe3db88c5247be7794bb",
    "jarFileModificationDate": "2014-01-18T11:45:23+11:00",
    "location": "/Users/timothyboye/ICT Freelance/Minecraft/Mod 0/jars/libraries/org/bouncycastle/bcprov-jdk15on/1.47/bcprov-jdk15on-1.47.jar",
    "javaRuntime": false
  },
  {
    "symbolicName": "jre",
    "version": {
      "major": 1,
      "minor": 0,
      "micro": 0,
      "qualifier": ""
    },
    "jarFileFingerprint": "c5d7b7bfab9b433c4b62aebbe76a564b6bcf8192",
    "jarFileModificationDate": "2013-08-08T12:11:00+10:00",
    "location": "/System/Library/Java/Extensions/mlibwrapper_jai.jar",
    "javaRuntime": true
  },
  {
    "symbolicName": "jinput-2.0.5",
    "version": {
      "major": -1,
      "minor": -1,
      "micro": -1,
      "qualifier": ""
    },
    "jarFileFingerprint": "39c7796b469a600f72380316f6b1f11db6c2c7c4",
    "jarFileModificationDate": "2014-01-18T11:45:39+11:00",
    "location": "/Users/timothyboye/ICT Freelance/Minecraft/Mod 0/jars/libraries/net/java/jinput/jinput/2.0.5/jinput-2.0.5.jar",
    "javaRuntime": false
  },
  {
    "symbolicName": "com.google.gson",
    "version": {
      "major": 2,
      "minor": 2,
      "micro": 2,
      "qualifier": ""
    },
    "jarFileFingerprint": "1f96456ca233dec780aa224bff076d8e8bca3908",
    "jarFileModificationDate": "2014-01-18T11:45:43+11:00",
    "location": "/Users/timothyboye/ICT Freelance/Minecraft/Mod 0/jars/libraries/com/google/code/gson/gson/2.2.2/gson-2.2.2.jar",
    "javaRuntime": false
  },
  {
    "symbolicName": "org.objectweb.asm.all.debug",
    "version": {
      "major": 4,
      "minor": 1,
      "micro": 0,
      "qualifier": ""
    },
    "jarFileFingerprint": "dd6ba5c392d4102458494e29f54f70ac534ec2a2",
    "jarFileModificationDate": "2014-01-18T11:44:13+11:00",
    "location": "/Users/timothyboye/ICT Freelance/Minecraft/Mod 0/jars/libraries/org/ow2/asm/asm-debug-all/4.1/asm-debug-all-4.1.jar",
    "javaRuntime": false
  },
  {
    "symbolicName": "jre",
    "version": {
      "major": 1,
      "minor": 0,
      "micro": 0,
      "qualifier": ""
    },
    "jarFileFingerprint": "06b897f357f111e205017803b1d10f972e8f1075",
    "jarFileModificationDate": "2013-08-08T12:15:41+10:00",
    "location": "/System/Library/Java/Extensions/j3dcore.jar",
    "javaRuntime": true
  },
  {
    "symbolicName": "com.paulscode.libraryjavasound",
    "version": {
      "major": 20101123,
      "minor": 0,
      "micro": 0,
      "qualifier": ""
    },
    "jarFileFingerprint": "5c5e304366f75f9eaa2e8cca546a1fb6109348b3",
    "jarFileModificationDate": "2014-01-18T11:45:05+11:00",
    "location": "/Users/timothyboye/ICT Freelance/Minecraft/Mod 0/jars/libraries/com/paulscode/libraryjavasound/20101123/libraryjavasound-20101123.jar",
    "javaRuntime": false
  },
  {
    "symbolicName": "jre",
    "version": {
      "major": 1,
      "minor": 0,
      "micro": 0,
      "qualifier": ""
    },
    "jarFileFingerprint": "51dbde992ee8e0ee2e9e1be38fcc6d3295ebc66e",
    "jarFileModificationDate": "2013-08-08T12:16:58+10:00",
    "location": "/System/Library/Java/Extensions/AppleScriptEngine.jar",
    "javaRuntime": true
  },
  {
    "symbolicName": "com.paulscode.codecjorbis",
    "version": {
      "major": 20101023,
      "minor": 0,
      "micro": 0,
      "qualifier": ""
    },
    "jarFileFingerprint": "c73b5636faf089d9f00e8732a829577de25237ee",
    "jarFileModificationDate": "2014-01-18T11:45:03+11:00",
    "location": "/Users/timothyboye/ICT Freelance/Minecraft/Mod 0/jars/libraries/com/paulscode/codecjorbis/20101023/codecjorbis-20101023.jar",
    "javaRuntime": false
  },
  {
    "symbolicName": "jre",
    "version": {
      "major": 1,
      "minor": 0,
      "micro": 0,
      "qualifier": ""
    },
    "jarFileFingerprint": "3992b52876ea5c35473e170f78781d8be91c6dd2",
    "jarFileModificationDate": "2013-11-24T10:15:25+11:00",
    "location": "/System/Library/Java/Extensions/QTJava.zip",
    "javaRuntime": true
  },
  {
    "symbolicName": "jre",
    "version": {
      "major": 1,
      "minor": 0,
      "micro": 0,
      "qualifier": ""
    },
    "jarFileFingerprint": "8dd971cde724dfec556b5701ff3c9b8bbd262677",
    "jarFileModificationDate": "2013-10-11T05:38:59+11:00",
    "location": "/System/Library/Java/JavaVirtualMachines/1.6.0.jdk/Contents/Home/lib/ext/apple_provider.jar",
    "javaRuntime": true
  },
  {
    "symbolicName": "org.apache.commons.io",
    "version": {
      "major": 2,
      "minor": 4,
      "micro": 0,
      "qualifier": ""
    },
    "jarFileFingerprint": "b1b6ea3b7e4aa4f492509a4952029cd8e48019ad",
    "jarFileModificationDate": "2014-01-18T11:45:36+11:00",
    "location": "/Users/timothyboye/ICT Freelance/Minecraft/Mod 0/jars/libraries/commons-io/commons-io/2.4/commons-io-2.4.jar",
    "javaRuntime": false
  },
  {
    "symbolicName": "jre",
    "version": {
      "major": 1,
      "minor": 0,
      "micro": 0,
      "qualifier": ""
    },
    "jarFileFingerprint": "e7533ef29283d456ddcc700ad2ccdd0c3452e464",
    "jarFileModificationDate": "2013-08-08T12:15:41+10:00",
    "location": "/System/Library/Java/Extensions/j3dutils.jar",
    "javaRuntime": true
  },
  {
    "symbolicName": "jre",
    "version": {
      "major": 1,
      "minor": 0,
      "micro": 0,
      "qualifier": ""
    },
    "jarFileFingerprint": "ea45c5d84b402679dd74825b0806a269a3cd4aee",
    "jarFileModificationDate": "2013-10-11T05:32:12+11:00",
    "location": "/System/Library/Java/JavaVirtualMachines/1.6.0.jdk/Contents/Classes/charsets.jar",
    "javaRuntime": true
  },
  {
    "symbolicName": "jre",
    "version": {
      "major": 1,
      "minor": 0,
      "micro": 0,
      "qualifier": ""
    },
    "jarFileFingerprint": "70e3f9e76e3d5884415516c0cee0855295bcb571",
    "jarFileModificationDate": "2013-10-11T05:22:21+11:00",
    "location": "/System/Library/Java/JavaVirtualMachines/1.6.0.jdk/Contents/Classes/jce.jar",
    "javaRuntime": true
  },
  {
    "symbolicName": "jre",
    "version": {
      "major": 1,
      "minor": 0,
      "micro": 0,
      "qualifier": ""
    },
    "jarFileFingerprint": "d57b4588c1c302ad017b0cf25de95dfb1b22e8fc",
    "jarFileModificationDate": "2013-11-08T01:06:58+11:00",
    "location": "/System/Library/Java/Extensions/MRJToolkit.jar",
    "javaRuntime": true
  },
  {
    "symbolicName": "com.paulscode.soundsystem",
    "version": {
      "major": 20120107,
      "minor": 0,
      "micro": 0,
      "qualifier": ""
    },
    "jarFileFingerprint": "419c05fe9be71f792b2d76cfc9b67f1ed0fec7f6",
    "jarFileModificationDate": "2014-01-18T11:45:08+11:00",
    "location": "/Users/timothyboye/ICT Freelance/Minecraft/Mod 0/jars/libraries/com/paulscode/soundsystem/20120107/soundsystem-20120107.jar",
    "javaRuntime": false
  },
  {
    "symbolicName": "argo-2.25_fixed",
    "version": {
      "major": -1,
      "minor": -1,
      "micro": -1,
      "qualifier": ""
    },
    "jarFileFingerprint": "751761ce15a3e3aaf3fc75b9f013ff8f7b88a585",
    "jarFileModificationDate": "2014-01-18T11:45:16+11:00",
    "location": "/Users/timothyboye/ICT Freelance/Minecraft/Mod 0/jars/libraries/argo/argo/2.25_fixed/argo-2.25_fixed.jar",
    "javaRuntime": false
  },
  {
    "symbolicName": "com.paulscode.librarylwjglopenal",
    "version": {
      "major": 20100824,
      "minor": 0,
      "micro": 0,
      "qualifier": ""
    },
    "jarFileFingerprint": "73e80d0794c39665aec3f62eee88ca91676674ef",
    "jarFileModificationDate": "2014-01-18T11:45:06+11:00",
    "location": "/Users/timothyboye/ICT Freelance/Minecraft/Mod 0/jars/libraries/com/paulscode/librarylwjglopenal/20100824/librarylwjglopenal-20100824.jar",
    "javaRuntime": false
  },
  {
    "symbolicName": "lzma-0.0.1",
    "version": {
      "major": -1,
      "minor": -1,
      "micro": -1,
      "qualifier": ""
    },
    "jarFileFingerprint": "521616dc7487b42bef0e803bd2fa3faf668101d7",
    "jarFileModificationDate": "2014-01-18T11:45:02+11:00",
    "location": "/Users/timothyboye/ICT Freelance/Minecraft/Mod 0/jars/libraries/lzma/lzma/0.0.1/lzma-0.0.1.jar",
    "javaRuntime": false
  },
  {
    "symbolicName": "jre",
    "version": {
      "major": 1,
      "minor": 0,
      "micro": 0,
      "qualifier": ""
    },
    "jarFileFingerprint": "0bb518175e479ab8291700f8e33ea16fccf4ae9d",
    "jarFileModificationDate": "2013-10-11T05:38:52+11:00",
    "location": "/System/Library/Java/JavaVirtualMachines/1.6.0.jdk/Contents/Classes/ui.jar",
    "javaRuntime": true
  },
  {
    "symbolicName": "net.sf.jopt-simple.jopt-simple",
    "version": {
      "major": 4,
      "minor": 5,
      "micro": 0,
      "qualifier": ""
    },
    "jarFileFingerprint": "6065cc95c661255349c1d0756657be17c29a4fd3",
    "jarFileModificationDate": "2014-01-18T11:44:59+11:00",
    "location": "/Users/timothyboye/ICT Freelance/Minecraft/Mod 0/jars/libraries/net/sf/jopt-simple/jopt-simple/4.5/jopt-simple-4.5.jar",
    "javaRuntime": false
  },
  {
    "symbolicName": "com.google.guava",
    "version": {
      "major": 14,
      "minor": 0,
      "micro": 0,
      "qualifier": ""
    },
    "jarFileFingerprint": "67b7be4ee7ba48e4828a42d6d5069761186d4a53",
    "jarFileModificationDate": "2014-01-18T11:45:30+11:00",
    "location": "/Users/timothyboye/ICT Freelance/Minecraft/Mod 0/jars/libraries/com/google/guava/guava/14.0/guava-14.0.jar",
    "javaRuntime": false
  },
  {
    "symbolicName": "org.apache.commons.lang3",
    "version": {
      "major": 3,
      "minor": 1,
      "micro": 0,
      "qualifier": ""
    },
    "jarFileFingerprint": "905075e6c80f206bbe6cf1e809d2caa69f420c76",
    "jarFileModificationDate": "2014-01-18T11:45:34+11:00",
    "location": "/Users/timothyboye/ICT Freelance/Minecraft/Mod 0/jars/libraries/org/apache/commons/commons-lang3/3.1/commons-lang3-3.1.jar",
    "javaRuntime": false
  },
  {
    "symbolicName": "jre",
    "version": {
      "major": 1,
      "minor": 0,
      "micro": 0,
      "qualifier": ""
    },
    "jarFileFingerprint": "6d342cc086f5c4bf834664ddcdfbb4f4166446a7",
    "jarFileModificationDate": "2013-10-11T05:22:21+11:00",
    "location": "/System/Library/Java/JavaVirtualMachines/1.6.0.jdk/Contents/Classes/jsse.jar",
    "javaRuntime": true
  },
  {
    "symbolicName": "jre",
    "version": {
      "major": 1,
      "minor": 0,
      "micro": 0,
      "qualifier": ""
    },
    "jarFileFingerprint": "1131fd02e5ae3337bb6f58f41b5bd785bfc3b2c2",
    "jarFileModificationDate": "2013-10-11T05:32:03+11:00",
    "location": "/System/Library/Java/JavaVirtualMachines/1.6.0.jdk/Contents/Home/lib/ext/localedata.jar",
    "javaRuntime": true
  },
  {
    "symbolicName": "jre",
    "version": {
      "major": 1,
      "minor": 0,
      "micro": 0,
      "qualifier": ""
    },
    "jarFileFingerprint": "a85d5af49e138a0adefc26bf22d2cfc8c754e6dd",
    "jarFileModificationDate": "2013-08-08T12:11:25+10:00",
    "location": "/System/Library/Java/Extensions/jai_codec.jar",
    "javaRuntime": true
  },
  {
    "symbolicName": "com.paulscode.codecwav",
    "version": {
      "major": 20101023,
      "minor": 0,
      "micro": 0,
      "qualifier": ""
    },
    "jarFileFingerprint": "12f031cfe88fef5c1dd36c563c0a3a69bd7261da",
    "jarFileModificationDate": "2014-01-18T11:45:04+11:00",
    "location": "/Users/timothyboye/ICT Freelance/Minecraft/Mod 0/jars/libraries/com/paulscode/codecwav/20101023/codecwav-20101023.jar",
    "javaRuntime": false
  },
  {
    "symbolicName": "net.java.jutils.jutils",
    "version": {
      "major": 1,
      "minor": 0,
      "micro": 0,
      "qualifier": ""
    },
    "jarFileFingerprint": "e12fe1fda814bd348c1579329c86943d2cd3c6a6",
    "jarFileModificationDate": "2014-01-18T11:45:41+11:00",
    "location": "/Users/timothyboye/ICT Freelance/Minecraft/Mod 0/jars/libraries/net/java/jutils/jutils/1.0.0/jutils-1.0.0.jar",
    "javaRuntime": false
  },
  {
    "symbolicName": "jre",
    "version": {
      "major": 1,
      "minor": 0,
      "micro": 0,
      "qualifier": ""
    },
    "jarFileFingerprint": "f0175c4c28f08b9236108499c33d6542c0bcd8b4",
    "jarFileModificationDate": "2013-08-08T12:15:41+10:00",
    "location": "/System/Library/Java/Extensions/j3daudio.jar",
    "javaRuntime": true
  },
  {
    "symbolicName": "jre",
    "version": {
      "major": 1,
      "minor": 0,
      "micro": 0,
      "qualifier": ""
    },
    "jarFileFingerprint": "21240ab7c12f378058cbb7a9b2f5b762dd30e1b8",
    "jarFileModificationDate": "2013-08-08T12:11:25+10:00",
    "location": "/System/Library/Java/Extensions/jai_core.jar",
    "javaRuntime": true
  },
  {
    "symbolicName": "lwjgl-2.9.0",
    "version": {
      "major": -1,
      "minor": -1,
      "micro": -1,
      "qualifier": ""
    },
    "jarFileFingerprint": "5654d06e61a1bba7ae1e7f5233e1106be64c91cd",
    "jarFileModificationDate": "2014-01-18T11:45:10+11:00",
    "location": "/Users/timothyboye/ICT Freelance/Minecraft/Mod 0/jars/libraries/org/lwjgl/lwjgl/lwjgl/2.9.0/lwjgl-2.9.0.jar",
    "javaRuntime": false
  },
  {
    "symbolicName": "jre",
    "version": {
      "major": 1,
      "minor": 0,
      "micro": 0,
      "qualifier": ""
    },
    "jarFileFingerprint": "17cb77e6b97b7d53eac15eb338d289d6ad70d64a",
    "jarFileModificationDate": "2013-10-11T05:36:08+11:00",
    "location": "/System/Library/Java/JavaVirtualMachines/1.6.0.jdk/Contents/Classes/classes.jar",
    "javaRuntime": true
  },
  {
    "symbolicName": "launchwrapper-1.8",
    "version": {
      "major": -1,
      "minor": -1,
      "micro": -1,
      "qualifier": ""
    },
    "jarFileFingerprint": "d4c0895977dd7f0b3f56281cee53a64d4c0c0322",
    "jarFileModificationDate": "2014-01-18T11:44:12+11:00",
    "location": "/Users/timothyboye/ICT Freelance/Minecraft/Mod 0/jars/libraries/net/minecraft/launchwrapper/1.8/launchwrapper-1.8.jar",
    "javaRuntime": false
  },
  {
    "symbolicName": "jre",
    "version": {
      "major": 1,
      "minor": 0,
      "micro": 0,
      "qualifier": ""
    },
    "jarFileFingerprint": "a84551888636d4e693dc9b483ad69a6a78ad9d74",
    "jarFileModificationDate": "2013-11-08T01:06:59+11:00",
    "location": "/System/Library/Java/JavaVirtualMachines/1.6.0.jdk/Contents/Home/lib/ext/dnsns.jar",
    "javaRuntime": true
  },
  {
    "symbolicName": "jre",
    "version": {
      "major": 1,
      "minor": 0,
      "micro": 0,
      "qualifier": ""
    },
    "jarFileFingerprint": "005810d865dab9bd200ea485d0e44c18a329aa26",
    "jarFileModificationDate": "2013-08-08T12:15:41+10:00",
    "location": "/System/Library/Java/Extensions/vecmath.jar",
    "javaRuntime": true
  },
  {
    "symbolicName": "jre",
    "version": {
      "major": 1,
      "minor": 0,
      "micro": 0,
      "qualifier": ""
    },
    "jarFileFingerprint": "63fbdd9c7e93573cc15ee487950217886be2aef6",
    "jarFileModificationDate": "2013-11-08T01:07:00+11:00",
    "location": "/System/Library/Java/Extensions/dns_sd.jar",
    "javaRuntime": true
  }
]